character_attributes/__init__.py
color/__init__.py
font/__init__.py
highlight/__init__.py
text_editing-2.0.0.dist-info/LICENSE
text_editing-2.0.0.dist-info/METADATA
text_editing-2.0.0.dist-info/WHEEL
text_editing-2.0.0.dist-info/top_level.txt
text_editing-2.0.0.dist-info/RECORD
