Metadata-Version: 2.1
Name: text-editing
Version: 2.0.0
Summary: Set of variables and functions for text editing.
Home-page: https://lassainora.fr/librairies/text_editing
Author: Axelle Viandier
Author-email: axelleviandier@lassainora.fr
Project-URL: Bug Tracker, https://github.com/LassaInora/Text_Editing/issues
Classifier: Programming Language :: Python :: 3.10
Classifier: License :: OSI Approved :: GNU General Public License v3 (GPLv3)
Classifier: Operating System :: OS Independent
Requires-Python: >=3.6
License-File: LICENSE
